badgers/__init__.py
badgers/core/__init__.py
badgers/core/base.py
badgers/core/pipeline.py
badgers/core/utils.py
badgers/core/decorators/__init__.py
badgers/core/decorators/tabular_data.py
badgers/core/decorators/time_series.py
badgers/generators/__init__.py
badgers/generators/geolocated_data/__init__.py
badgers/generators/graph/__init__.py
badgers/generators/graph/missingness.py
badgers/generators/image/__init__.py
badgers/generators/tabular_data/__init__.py
badgers/generators/tabular_data/drift.py
badgers/generators/tabular_data/imbalance.py
badgers/generators/tabular_data/missingness.py
badgers/generators/tabular_data/noise.py
badgers/generators/tabular_data/outliers.py
badgers/generators/text/__init__.py
badgers/generators/text/typos.py
badgers/generators/time_series/__init__.py
badgers/generators/time_series/changepoints.py
badgers/generators/time_series/missingness.py
badgers/generators/time_series/noise.py
badgers/generators/time_series/outliers.py
badgers/generators/time_series/patterns.py
badgers/generators/time_series/seasons.py
badgers/generators/time_series/transmission_errors.py
badgers/generators/time_series/trends.py
badgers/generators/time_series/utils.py
badgers-0.0.10.dist-info/METADATA
badgers-0.0.10.dist-info/WHEEL
badgers-0.0.10.dist-info/licenses/LICENSE
badgers-0.0.10.dist-info/RECORD
