Metadata-Version: 2.4
Name: badgers
Version: 0.0.10
Summary: Badgers: bad data generators
Project-URL: Homepage, https://github.com/Fraunhofer-IESE/badgers
Project-URL: Bug Tracker, https://github.com/Fraunhofer-IESE/badgers/issues
Author-email: Julien Siebert <julien.siebert@iese.fraunhofer.de>
Maintainer-email: Julien Siebert <julien.siebert@iese.fraunhofer.de>
License: BSD 3-Clause License
License-File: LICENSE
Keywords: bad data,data quality,data science
Classifier: Development Status :: 1 - Planning
Classifier: License :: OSI Approved :: BSD License
Classifier: Operating System :: OS Independent
Classifier: Programming Language :: Python :: 3
Requires-Python: >=3.8
Requires-Dist: networkx
Requires-Dist: numpy
Requires-Dist: pandas
Requires-Dist: scikit-learn
Requires-Dist: scipy
